Metadata-Version: 1.0
Name: bi-distributions
Version: 0.1
Summary: Gaussian distributions
Home-page: UNKNOWN
Author: Rakesh
Author-email: UNKNOWN
License: UNKNOWN
Platform: UNKNOWN
